glhooks/config.py
glhooks/git.py
glhooks/server.py
glhooks/system.py
glhooks/utils.py
glhooks/__init__.py
glhooks/__main__.py
glhooks/mailer/attachment.py
glhooks/mailer/compat.py
glhooks/mailer/mailer.py
glhooks/mailer/messages.py
glhooks/mailer/utils.py
glhooks/mailer/__init__.py
glhooks-0.1.0.dist-info/DESCRIPTION.rst
glhooks-0.1.0.dist-info/METADATA
glhooks-0.1.0.dist-info/pydist.json
glhooks-0.1.0.dist-info/RECORD
glhooks-0.1.0.dist-info/top_level.txt
glhooks-0.1.0.dist-info/WHEEL
